bipolar_explorer_mne/__init__.py
bipolar_explorer_mne/__version__.py
bipolar_explorer_mne/bipolar_explorer.py
bipolar_explorer_mne/visualization.py
bipolar_explorer_mne-0.1.3.dist-info/licenses/LICENSE
bipolar_explorer_mne-0.1.3.dist-info/METADATA
bipolar_explorer_mne-0.1.3.dist-info/WHEEL
bipolar_explorer_mne-0.1.3.dist-info/top_level.txt
bipolar_explorer_mne-0.1.3.dist-info/RECORD
