Metadata-Version: 2.4
Name: bipolar-explorer-mne
Version: 0.1.3
Summary: A tool for exploring bipolar montages in MNE files.
Author-email: Ana Sofia Carmo <anascacais@gmail.com>
License: BSD 3-Clause License
Project-URL: Repository, https://github.com/anascacais/BipolarExplorerMNE
Classifier: Programming Language :: Python :: 3
Classifier: Operating System :: OS Independent
License-File: LICENSE
Requires-Dist: mne
Requires-Dist: plotly
Requires-Dist: pandas
Requires-Dist: plotly-resampler
Dynamic: license-file
